krypt_shade/__init__.py
krypt_shade/color.py
krypt_shade-0.1.dist-info/METADATA
krypt_shade-0.1.dist-info/WHEEL
krypt_shade-0.1.dist-info/top_level.txt
krypt_shade-0.1.dist-info/RECORD
