Metadata-Version: 2.1
Name: krypt_shade
Version: 0.1
Summary: A library to manipulate colors (HEX to RGB, brightness adjustment, shade generation)
Home-page: https://github.com/krypton-0x00/krypt_shade
Author: krypton-0x00
Author-email: krypton0x00@gmail.com
Classifier: Programming Language :: Python :: 3
Classifier: License :: OSI Approved :: MIT License
Classifier: Operating System :: OS Independent
Requires-Python: >=3.6
